composor/__init__.py
composor-0.0.0.dist-info/METADATA
composor-0.0.0.dist-info/WHEEL
composor-0.0.0.dist-info/top_level.txt
composor-0.0.0.dist-info/RECORD
